bircher/__init__.py
bircher/_bircher.py
bircher/models.py
bircher/utils.py
bircher/widgets/__init__.py
bircher/widgets/_consensus_image_list.py
bircher/widgets/_image_table_model.py
bircher/widgets/_image_table_view.py
bircher-0.1.0rc5.dist-info/LICENSE
bircher-0.1.0rc5.dist-info/METADATA
bircher-0.1.0rc5.dist-info/WHEEL
bircher-0.1.0rc5.dist-info/entry_points.txt
bircher-0.1.0rc5.dist-info/top_level.txt
bircher-0.1.0rc5.dist-info/RECORD
