Metadata-Version: 2.1
Name: bircher
Version: 0.1.0rc5
Summary: A tool for bioimage data validation and archival
Author-email: Jonas Windhager <jonas@windhager.io>
Classifier: Intended Audience :: Science/Research
Classifier: License :: OSI Approved :: GNU General Public License v3 (GPLv3)
Classifier: Operating System :: OS Independent
Requires-Python: <3.12,>=3.10
License-File: LICENSE
Requires-Dist: aicsimageio[all]
Requires-Dist: pandas
Requires-Dist: qtpy
Provides-Extra: bioformats
Requires-Dist: bioformats-jar ; extra == 'bioformats'
Provides-Extra: czi
Requires-Dist: aicspylibczi ; extra == 'czi'
Requires-Dist: fsspec ; extra == 'czi'
Provides-Extra: lif
Requires-Dist: readlif ; extra == 'lif'
Provides-Extra: pyside6
Requires-Dist: pyside6-essentials ; extra == 'pyside6'
